{
  "_type": "export",
  "__export_format": 4,
  "__export_date": "2020-06-05T16:10:34.498Z",
  "__export_source": "insomnia.desktop.app:v7.1.1",
  "resources": [
    {
      "_id": "req_c77da87d99d4496fa1c17f62326d7c8f",
      "authentication": {},
      "body": {},
      "created": 1591192889947,
      "description": "",
      "headers": [],
      "isPrivate": false,
      "metaSortKey": -1591192889947,
      "method": "GET",
      "modified": 1591319655549,
      "name": "List students",
      "parameters": [],
      "parentId": "fld_abdab1ed8cf245cd93b7f81a6904a801",
      "settingDisableRenderRequestBody": false,
      "settingEncodeUrl": true,
      "settingFollowRedirects": "global",
      "settingRebuildPath": true,
      "settingSendCookies": true,
      "settingStoreCookies": true,
      "url": "http://localhost:3000/students",
      "_type": "request"
    },
    {
      "_id": "fld_abdab1ed8cf245cd93b7f81a6904a801",
      "created": 1591189895196,
      "description": "",
      "environment": {},
      "environmentPropertyOrder": null,
      "metaSortKey": -1591189895196,
      "modified": 1591189895196,
      "name": "Grupo A - Desafio",
      "parentId": "wrk_1495c2d5cc8a4ed587a3cc902b05c52f",
      "_type": "request_group"
    },
    {
      "_id": "wrk_1495c2d5cc8a4ed587a3cc902b05c52f",
      "created": 1585225555888,
      "description": "",
      "modified": 1585225555888,
      "name": "Insomnia",
      "parentId": null,
      "_type": "workspace"
    },
    {
      "_id": "req_fe05588c9e3446a79a858eecacac9129",
      "authentication": {},
      "body": {},
      "created": 1591231004855,
      "description": "",
      "headers": [],
      "isPrivate": false,
      "metaSortKey": -1591192722377.5,
      "method": "GET",
      "modified": 1591231019549,
      "name": "Get by specified student",
      "parameters": [],
      "parentId": "fld_abdab1ed8cf245cd93b7f81a6904a801",
      "settingDisableRenderRequestBody": false,
      "settingEncodeUrl": true,
      "settingFollowRedirects": "global",
      "settingRebuildPath": true,
      "settingSendCookies": true,
      "settingStoreCookies": true,
      "url": "http://localhost:3000/student/13",
      "_type": "request"
    },
    {
      "_id": "req_8048557ec0d4409d9905a3f0e4bbc309",
      "authentication": {},
      "body": {},
      "created": 1591192554808,
      "description": "",
      "headers": [],
      "isPrivate": false,
      "metaSortKey": -1591192554808,
      "method": "DELETE",
      "modified": 1591232387846,
      "name": "Delete a student",
      "parameters": [],
      "parentId": "fld_abdab1ed8cf245cd93b7f81a6904a801",
      "settingDisableRenderRequestBody": false,
      "settingEncodeUrl": true,
      "settingFollowRedirects": "global",
      "settingRebuildPath": true,
      "settingSendCookies": true,
      "settingStoreCookies": true,
      "url": "http://localhost:3000/student/23",
      "_type": "request"
    },
    {
      "_id": "req_fc31304328514ee8b2d905efaa379473",
      "authentication": {},
      "body": {
        "mimeType": "application/json",
        "text": "{\n\t\"name\": \"AAAAAAAAAAAAAAA\",\n\t\"email\": \"@gmail.com\"\n}"
      },
      "created": 1591191443886,
      "description": "",
      "headers": [
        {
          "id": "pair_67fbe7f11bc049bcae65123daccab43f",
          "name": "Content-Type",
          "value": "application/json"
        }
      ],
      "isPrivate": false,
      "metaSortKey": -1591191443886,
      "method": "PUT",
      "modified": 1591213507481,
      "name": "Edit a student",
      "parameters": [],
      "parentId": "fld_abdab1ed8cf245cd93b7f81a6904a801",
      "settingDisableRenderRequestBody": false,
      "settingEncodeUrl": true,
      "settingFollowRedirects": "global",
      "settingRebuildPath": true,
      "settingSendCookies": true,
      "settingStoreCookies": true,
      "url": "http://localhost:3000/student/17",
      "_type": "request"
    },
    {
      "_id": "req_d9e0709f506247fe8ce1b07c35a87bb1",
      "authentication": {},
      "body": {
        "mimeType": "application/json",
        "text": "{\n\t\"name\": \"fernando gordo\",\n\t\"email\": \"fernando@gmail.com\",\n\t\"cpf\": \"87336622072\"\n}"
      },
      "created": 1591189908737,
      "description": "",
      "headers": [
        {
          "id": "pair_943b1b9ebb2a4eea8f2f165db8be319c",
          "name": "Content-Type",
          "value": "application/json"
        }
      ],
      "isPrivate": false,
      "metaSortKey": -1591189908737,
      "method": "POST",
      "modified": 1591372407839,
      "name": "Create a student",
      "parameters": [],
      "parentId": "fld_abdab1ed8cf245cd93b7f81a6904a801",
      "settingDisableRenderRequestBody": false,
      "settingEncodeUrl": true,
      "settingFollowRedirects": "global",
      "settingRebuildPath": true,
      "settingSendCookies": true,
      "settingStoreCookies": true,
      "url": "http://localhost:3000/student",
      "_type": "request"
    },
    {
      "_id": "env_8912291a2d62a642bcc4a3fb7947d593b8096866",
      "color": null,
      "created": 1585225555954,
      "data": {},
      "dataPropertyOrder": null,
      "isPrivate": false,
      "metaSortKey": 1585225555954,
      "modified": 1585225555954,
      "name": "Base Environment",
      "parentId": "wrk_1495c2d5cc8a4ed587a3cc902b05c52f",
      "_type": "environment"
    },
    {
      "_id": "jar_8912291a2d62a642bcc4a3fb7947d593b8096866",
      "cookies": [
        {
          "creation": "2020-04-15T16:11:47.834Z",
          "domain": "localhost",
          "hostOnly": true,
          "httpOnly": true,
          "id": "5670586703931071",
          "key": "root",
          "lastAccessed": "2020-04-15T21:39:23.298Z",
          "path": "/",
          "value": "s%3Am2ZbX4zjrIz3yNIf3XtdQC3n4g85zaFh.EchuyugYUrzN%2Bw%2BjUbjyKdLOsLc30ibF0wJA38ZGQy0"
        },
        {
          "creation": "2020-05-21T16:55:52.034Z",
          "domain": "linkedin.com",
          "expires": "2020-05-22T16:55:51.000Z",
          "extensions": [
            "SameSite=None"
          ],
          "hostOnly": false,
          "id": "565780450889739",
          "key": "lidc",
          "lastAccessed": "2020-05-21T16:55:52.034Z",
          "path": "/",
          "secure": true,
          "value": "\"b=VB31:g=3119:u=1:i=1590080151:t=1590166551:s=AQFI3i8CUs3IGQpfp_DZA5rI3AwmRESc\""
        }
      ],
      "created": 1585225555956,
      "modified": 1590080152036,
      "name": "Default Jar",
      "parentId": "wrk_1495c2d5cc8a4ed587a3cc902b05c52f",
      "_type": "cookie_jar"
    }
  ]
}